starlette_admin/__init__.py
starlette_admin/_types.py
starlette_admin/actions.py
starlette_admin/auth.py
starlette_admin/base.py
starlette_admin/converters.py
starlette_admin/exceptions.py
starlette_admin/fields.py
starlette_admin/helpers.py
starlette_admin/i18n.py
starlette_admin/py.typed
starlette_admin/views.py
starlette_admin/contrib/__init__.py
starlette_admin/contrib/beanie/__init__.py
starlette_admin/contrib/beanie/admin.py
starlette_admin/contrib/beanie/converters.py
starlette_admin/contrib/beanie/helpers.py
starlette_admin/contrib/beanie/view.py
starlette_admin/contrib/mongoengine/__init__.py
starlette_admin/contrib/mongoengine/admin.py
starlette_admin/contrib/mongoengine/converters.py
starlette_admin/contrib/mongoengine/exceptions.py
starlette_admin/contrib/mongoengine/fields.py
starlette_admin/contrib/mongoengine/helpers.py
starlette_admin/contrib/mongoengine/view.py
starlette_admin/contrib/odmantic/__init__.py
starlette_admin/contrib/odmantic/admin.py
starlette_admin/contrib/odmantic/converters.py
starlette_admin/contrib/odmantic/exceptions.py
starlette_admin/contrib/odmantic/helpers.py
starlette_admin/contrib/odmantic/middleware.py
starlette_admin/contrib/odmantic/view.py
starlette_admin/contrib/sqla/__init__.py
starlette_admin/contrib/sqla/admin.py
starlette_admin/contrib/sqla/converters.py
starlette_admin/contrib/sqla/exceptions.py
starlette_admin/contrib/sqla/fields.py
starlette_admin/contrib/sqla/helpers.py
starlette_admin/contrib/sqla/middleware.py
starlette_admin/contrib/sqla/view.py
starlette_admin/contrib/sqla/ext/__init__.py
starlette_admin/contrib/sqla/ext/pydantic.py
starlette_admin/contrib/sqlmodel/__init__.py
starlette_admin/contrib/sqlmodel/admin.py
starlette_admin/contrib/sqlmodel/view.py
starlette_admin/statics/css/dt.checkboxes.css
starlette_admin/statics/css/dt.min.css
starlette_admin/statics/css/flatpickr.min.css
starlette_admin/statics/css/fontawesome.min.css
starlette_admin/statics/css/jsoneditor.min.css
starlette_admin-0.15.0.dist-info/METADATA
starlette_admin-0.15.0.dist-info/WHEEL
starlette_admin-0.15.0.dist-info/licenses/LICENSE
starlette_admin-0.15.0.dist-info/RECORD
