Metadata-Version: 2.4
Name: starlette-admin
Version: 0.15.0
Summary: Fast, beautiful and extensible administrative interface framework for Starlette/FastApi applications
Project-URL: Homepage, https://github.com/jowilf/starlette-admin
Project-URL: Documentation, https://jowilf.github.io/starlette-admin
Project-URL: Repository, https://github.com/jowilf/starlette-admin
Project-URL: Changelog, https://jowilf.github.io/starlette-admin/changelog/
Author-email: Jocelin Hounon <hounonj@gmail.com>
License-Expression: MIT
License-File: LICENSE
Keywords: admin,dashboard,datatables,fastapi,mongoengine,odmantic,sqlalchemy,sqlmodel,starlette
Classifier: Development Status :: 4 - Beta
Classifier: Environment :: Web Environment
Classifier: Framework :: AsyncIO
Classifier: Intended Audience :: Developers
Classifier: License :: OSI Approved :: MIT License
Classifier: Operating System :: OS Independent
Classifier: Programming Language :: Python
Classifier: Programming Language :: Python :: 3.9
Classifier: Programming Language :: Python :: 3.10
Classifier: Programming Language :: Python :: 3.11
Classifier: Programming Language :: Python :: 3.12
Classifier: Programming Language :: Python :: 3.13
Classifier: Topic :: Software Development :: Libraries :: Python Modules
Requires-Python: >=3.9
Requires-Dist: jinja2<4,>=3
Requires-Dist: python-multipart
Requires-Dist: starlette
Provides-Extra: cov
Requires-Dist: coverage[toml]<7.7.0,>=7.0.0; extra == 'cov'
Provides-Extra: dev
Requires-Dist: pre-commit<4.1.0,>=2.20.0; extra == 'dev'
Requires-Dist: uvicorn<0.33.0,>=0.20.0; extra == 'dev'
Provides-Extra: doc
Requires-Dist: mkdocs-material<10.0.0,>=9.0.0; extra == 'doc'
Requires-Dist: mkdocs-static-i18n<1.3,>=1.2.3; extra == 'doc'
Requires-Dist: mkdocs<2.0.0,>=1.4.2; extra == 'doc'
Requires-Dist: mkdocstrings[python]<0.27.0,>=0.19.0; extra == 'doc'
Provides-Extra: i18n
Requires-Dist: babel>=2.13.0; extra == 'i18n'
Provides-Extra: test
Requires-Dist: aiomysql<0.3.0,>=0.1.1; extra == 'test'
Requires-Dist: aiosqlite<0.21.0,>=0.17.0; extra == 'test'
Requires-Dist: arrow<1.4.0,>=1.2.3; extra == 'test'
Requires-Dist: asyncpg<0.31.0,>=0.27.0; extra == 'test'
Requires-Dist: backports-zoneinfo; (python_version < '3.9') and extra == 'test'
Requires-Dist: beanie<2.0.0; extra == 'test'
Requires-Dist: black==25.1.0; extra == 'test'
Requires-Dist: colour<0.2.0,>=0.1.5; extra == 'test'
Requires-Dist: fasteners==0.19; extra == 'test'
Requires-Dist: httpx<0.29.0,>=0.23.3; extra == 'test'
Requires-Dist: itsdangerous<2.3.0,>=2.2.0; extra == 'test'
Requires-Dist: mongoengine<0.30.0,>=0.25.0; extra == 'test'
Requires-Dist: mypy==1.15.0; extra == 'test'
Requires-Dist: passlib<1.8.0,>=1.7.4; extra == 'test'
Requires-Dist: phonenumbers<8.14.0,>=8.13.3; extra == 'test'
Requires-Dist: pillow<11.1.0,>=9.4.0; extra == 'test'
Requires-Dist: psycopg2-binary<3.0.0,>=2.9.5; extra == 'test'
Requires-Dist: pydantic[email]<2.10.0,>=1.10.2; extra == 'test'
Requires-Dist: pymysql[rsa]<1.2.0,>=1.0.2; extra == 'test'
Requires-Dist: pytest-asyncio<0.25.0,>=0.24.0; extra == 'test'
Requires-Dist: pytest<8.4.0,>=8.3.0; extra == 'test'
Requires-Dist: ruff==0.11.9; extra == 'test'
Requires-Dist: sqlalchemy-file<0.7.0,>=0.5.0; extra == 'test'
Requires-Dist: sqlalchemy-utils<0.42.0,>=0.40.0; extra == 'test'
Requires-Dist: sqlmodel<0.1.0,>=0.0.11; extra == 'test'
Requires-Dist: tinydb<4.9.0,>=4.7.0; extra == 'test'
